ShenruLijieTypescript/README.md
ShenruLijieTypescript/__init__.py
ShenruLijieTypescript/__main__.py
ShenruLijieTypescript/file.epub
ShenruLijieTypescript/index.html
ShenruLijieTypescript/css/__init__.py
ShenruLijieTypescript/css/annotations.css
ShenruLijieTypescript/css/main.css
ShenruLijieTypescript/css/normalize.css
ShenruLijieTypescript/css/popup.css
ShenruLijieTypescript/font/__init__.py
ShenruLijieTypescript/font/fontello.eot
ShenruLijieTypescript/font/fontello.svg
ShenruLijieTypescript/font/fontello.ttf
ShenruLijieTypescript/font/fontello.woff
ShenruLijieTypescript/img/__init__.py
ShenruLijieTypescript/img/annotator-glyph-sprite.png
ShenruLijieTypescript/img/annotator-icon-sprite.png
ShenruLijieTypescript/img/apple-touch-icon.png
ShenruLijieTypescript/img/cancelfullscreen.png
ShenruLijieTypescript/img/close.png
ShenruLijieTypescript/img/fullscreen.png
ShenruLijieTypescript/img/loader.gif
ShenruLijieTypescript/img/menu-icon.png
ShenruLijieTypescript/img/save.png
ShenruLijieTypescript/img/saved.png
ShenruLijieTypescript/img/settings-s.png
ShenruLijieTypescript/img/settings.png
ShenruLijieTypescript/img/star.png
ShenruLijieTypescript/js/__init__.py
ShenruLijieTypescript/js/epub.js
ShenruLijieTypescript/js/epub.min.js
ShenruLijieTypescript/js/epub.min.map
ShenruLijieTypescript/js/hooks.min.js
ShenruLijieTypescript/js/hooks.min.map
ShenruLijieTypescript/js/reader.js
ShenruLijieTypescript/js/reader.js.map
ShenruLijieTypescript/js/reader.min.js
ShenruLijieTypescript/js/reader.min.map
ShenruLijieTypescript/js/hooks/__init__.py
ShenruLijieTypescript/js/hooks/extensions/__init__.py
ShenruLijieTypescript/js/hooks/extensions/highlight.js
ShenruLijieTypescript/js/libs/__init__.py
ShenruLijieTypescript/js/libs/jquery.min.js
ShenruLijieTypescript/js/libs/localforage.min.js
ShenruLijieTypescript/js/libs/screenfull.js
ShenruLijieTypescript/js/libs/screenfull.min.js
ShenruLijieTypescript/js/libs/zip.min.js
ShenruLijieTypescript/js/plugins/__init__.py
shenru_lijie_typescript-2024.3.5.0.dist-info/METADATA
shenru_lijie_typescript-2024.3.5.0.dist-info/WHEEL
shenru_lijie_typescript-2024.3.5.0.dist-info/entry_points.txt
shenru_lijie_typescript-2024.3.5.0.dist-info/top_level.txt
shenru_lijie_typescript-2024.3.5.0.dist-info/RECORD
